flexygen/__init__.py
flexygen/data.py
flexygen/flexygen.py
flexygen/sentence_level.py
flexygen/utils.py
flexygen/mixins/__init__.py
flexygen/mixins/base.py
flexygen/mixins/generation.py
flexygen-0.0.5.dist-info/licenses/LICENSE
flexygen-0.0.5.dist-info/METADATA
flexygen-0.0.5.dist-info/WHEEL
flexygen-0.0.5.dist-info/top_level.txt
flexygen-0.0.5.dist-info/RECORD
