Metadata-Version: 2.4
Name: FlexyGen
Version: 0.0.5
Summary: An easy-to-use LLM controllable generation tool
Home-page: https://github.com/Liadrinz/flexygen
Author: Yuang Cai
Author-email: Yuang Cai <cyang.bupt@foxmail.com>
License-Expression: Apache-2.0
Project-URL: Homepage, https://github.com/Liadrinz/FlexyGen
Project-URL: Issues, https://github.com/Liadrinz/FlexyGen/issues
Classifier: Programming Language :: Python :: 3
Classifier: Operating System :: OS Independent
Requires-Python: >=3.8
License-File: LICENSE
Dynamic: author
Dynamic: home-page
Dynamic: license-file
